fastdaisy_admin/__init__.py
fastdaisy_admin/_menu.py
fastdaisy_admin/_queries.py
fastdaisy_admin/_types.py
fastdaisy_admin/_validators.py
fastdaisy_admin/actions.py
fastdaisy_admin/application.py
fastdaisy_admin/decorators.py
fastdaisy_admin/exceptions.py
fastdaisy_admin/fields.py
fastdaisy_admin/filters.py
fastdaisy_admin/formatters.py
fastdaisy_admin/forms.py
fastdaisy_admin/helpers.py
fastdaisy_admin/middleware.py
fastdaisy_admin/models.py
fastdaisy_admin/pagination.py
fastdaisy_admin/templating.py
fastdaisy_admin/widgets.py
fastdaisy_admin/auth/__init__.py
fastdaisy_admin/auth/command.py
fastdaisy_admin/auth/discover.py
fastdaisy_admin/auth/models.py
fastdaisy_admin/auth/service.py
fastdaisy_admin/statics/build/tailwind.css
fastdaisy_admin/statics/css/extra_styles.css
fastdaisy_admin/statics/css/flatpickr.min.css
fastdaisy_admin/statics/css/fontawesome.min.css
fastdaisy_admin/statics/css/styles.css
fastdaisy_admin/statics/js/flatpickr.min.js
fastdaisy_admin/statics/js/jquery.min.js
fastdaisy_admin/statics/js/main.js
fastdaisy_admin/statics/js/theme-change.js
fastdaisy_admin/statics/webfonts/fa-brands-400.woff2
fastdaisy_admin/statics/webfonts/fa-regular-400.woff2
fastdaisy_admin/statics/webfonts/fa-solid-900.woff2
fastdaisy_admin/statics/webfonts/tabler-icons.woff2
fastdaisy_admin/templates/fastdaisy_admin/_macros.html
fastdaisy_admin/templates/fastdaisy_admin/actions.html
fastdaisy_admin/templates/fastdaisy_admin/base.html
fastdaisy_admin/templates/fastdaisy_admin/create.html
fastdaisy_admin/templates/fastdaisy_admin/delete_confirmation.html
fastdaisy_admin/templates/fastdaisy_admin/delete_selected_confirmation.html
fastdaisy_admin/templates/fastdaisy_admin/edit.html
fastdaisy_admin/templates/fastdaisy_admin/error.html
fastdaisy_admin/templates/fastdaisy_admin/index.html
fastdaisy_admin/templates/fastdaisy_admin/layout.html
fastdaisy_admin/templates/fastdaisy_admin/list.html
fastdaisy_admin/templates/fastdaisy_admin/login.html
fastdaisy_admin-0.0.81.dist-info/METADATA
fastdaisy_admin-0.0.81.dist-info/WHEEL
fastdaisy_admin-0.0.81.dist-info/entry_points.txt
fastdaisy_admin-0.0.81.dist-info/licenses/LICENSE.md
fastdaisy_admin-0.0.81.dist-info/RECORD
