Metadata-Version: 2.4
Name: fastdaisy-admin
Version: 0.0.81
Summary: Admin for FastAPI and Starlette
Project-URL: Source, https://github.com/BhuwanPandey/fastdaisy-admin
Project-URL: Bug Tracker, https://github.com/BhuwanPandey/fastdaisy-admin/issues
Project-URL: PyPI, https://pypi.org/project/fastdaisy-admin
Author-email: Bhuwan Pandey <bhuwan.pandu12345@gmail.com>
License-Expression: MIT
License-File: LICENSE.md
Keywords: admin,daisyui,fastapi,sqlalchemy,starlette
Classifier: Development Status :: 3 - Alpha
Classifier: Environment :: Web Environment
Classifier: Framework :: FastAPI
Classifier: Intended Audience :: Developers
Classifier: License :: OSI Approved :: MIT License
Classifier: Operating System :: OS Independent
Classifier: Programming Language :: Python :: 3
Classifier: Programming Language :: Python :: 3.10
Classifier: Programming Language :: Python :: 3.11
Classifier: Programming Language :: Python :: 3.12
Classifier: Programming Language :: Python :: 3.13
Classifier: Topic :: Internet :: WWW/HTTP
Requires-Python: >=3.10
Requires-Dist: bcrypt>=5.0.0
Requires-Dist: itsdangerous>=2.2.0
Requires-Dist: jinja2>=3.1.6
Requires-Dist: python-multipart>=0.0.20
Requires-Dist: sqlalchemy>=2.0.43
Requires-Dist: starlette>=0.47.3
Requires-Dist: typer>=0.19.2
Requires-Dist: wtforms>=3.2.1
